{"lastModified":1778041909878,"boardState":"[{\"n\":1,\"subCells\":[{\"n\":3,\"id\":171764500,\"parentId\":58285008,\"missingNum\":true},{\"n\":6,\"id\":-1155390797,\"parentId\":58285008},{\"n\":4,\"id\":159336380,\"parentId\":58285008,\"missingNum\":true},{\"n\":-1,\"subCells\":[{\"n\":2,\"id\":-1654755058,\"parentId\":-1008570957},{\"n\":8,\"id\":1735871994,\"parentId\":2104685455}],\"id\":2047813958,\"parentId\":58285008,\"missingNum\":true},{\"n\":-1,\"subCells\":[{\"n\":2,\"id\":-202969883,\"parentId\":1337238349},{\"n\":5,\"id\":547632565,\"parentId\":472306486}],\"id\":387171845,\"parentId\":58285008,\"missingNum\":true},{\"n\":-1,\"subCells\":[{\"n\":5,\"id\":-1748721028,\"parentId\":326368928},{\"n\":8,\"id\":314638197,\"parentId\":-1117821225}],\"id\":-1246820117,\"parentId\":58285008,\"missingNum\":true},{\"n\":9,\"id\":1489174573,\"parentId\":58285008,\"missingNum\":true},{\"n\":7,\"id\":1692687284,\"parentId\":58285008,\"missingNum\":true},{\"n\":1,\"id\":989340900,\"parentId\":58285008,\"missingNum\":true}],\"id\":-509133772,\"parentId\":58285008},{\"n\":2,\"subCells\":[{\"n\":9,\"parentN\":2,\"id\":521757297,\"parentId\":1168421433,\"missingNum\":true},{\"n\":2,\"parentN\":2,\"id\":296144743,\"parentId\":1168421433},{\"n\":8,\"parentN\":2,\"id\":-31357299,\"parentId\":1168421433,\"missingNum\":true},{\"n\":7,\"parentN\":2,\"id\":-1111573502,\"parentId\":1168421433},{\"n\":3,\"parentN\":2,\"id\":916688775,\"parentId\":1168421433,\"missingNum\":true},{\"n\":-1,\"subCells\":[{\"n\":1,\"id\":-1637311152,\"parentId\":-934724770},{\"n\":6,\"id\":351879892,\"parentId\":-993078589}],\"parentN\":2,\"id\":-553003687,\"parentId\":1168421433,\"missingNum\":true},{\"n\":5,\"parentN\":2,\"id\":800915570,\"parentId\":1168421433,\"missingNum\":true},{\"n\":4,\"parentN\":2,\"id\":941494692,\"parentId\":1168421433},{\"n\":-1,\"subCells\":[{\"n\":6,\"id\":-235419261,\"parentId\":101669228}],\"parentN\":2,\"id\":-1437126342,\"parentId\":1168421433,\"missingNum\":true}],\"id\":1670972577,\"parentId\":1168421433},{\"n\":3,\"subCells\":[{\"n\":7,\"parentN\":3,\"id\":638270486,\"parentId\":-455109981,\"missingNum\":true},{\"n\":1,\"parentN\":3,\"id\":428837355,\"parentId\":-455109981},{\"n\":5,\"parentN\":3,\"id\":-602404581,\"parentId\":-455109981,\"missingNum\":true},{\"n\":-1,\"subCells\":[{\"n\":4,\"id\":-1706595090,\"parentId\":-815427615},{\"n\":6,\"id\":938560572,\"parentId\":1878236976}],\"parentN\":3,\"id\":-61495235,\"parentId\":-455109981,\"missingNum\":true},{\"n\":-1,\"subCells\":[{\"n\":2,\"id\":366622994,\"parentId\":1798171115},{\"n\":4,\"id\":-361904386,\"parentId\":1024182111},{\"n\":6,\"id\":-1068059918,\"parentId\":-1436960281}],\"parentN\":3,\"id\":-1746355267,\"parentId\":-455109981,\"missingNum\":true},{\"n\":9,\"parentN\":3,\"id\":769465110,\"parentId\":-455109981},{\"n\":3,\"parentN\":3,\"id\":827737468,\"parentId\":-455109981,\"missingNum\":true},{\"n\":8,\"parentN\":3,\"id\":-1814134422,\"parentId\":-455109981},{\"n\":-1,\"subCells\":[{\"n\":2,\"id\":-2059322272,\"parentId\":1071821242},{\"n\":6,\"id\":128252164,\"parentId\":1624224031}],\"parentN\":3,\"id\":1742698049,\"parentId\":-455109981,\"missingNum\":true}],\"id\":1500806256,\"parentId\":-455109981},{\"n\":4,\"subCells\":[{\"n\":4,\"parentN\":4,\"id\":-2133454154,\"parentId\":798016924,\"missingNum\":true},{\"n\":9,\"parentN\":4,\"id\":834525469,\"parentId\":798016924},{\"n\":3,\"parentN\":4,\"id\":-1075549277,\"parentId\":798016924},{\"n\":-1,\"subCells\":[{\"n\":2,\"id\":2072909945,\"parentId\":101941396},{\"n\":8,\"id\":-1840873633,\"parentId\":-1485117022}],\"parentN\":4,\"id\":-964836825,\"parentId\":798016924,\"missingNum\":true},{\"n\":-1,\"subCells\":[{\"n\":1,\"id\":-956460423,\"parentId\":490626820},{\"n\":2,\"id\":-1594419605,\"parentId\":-3554965},{\"n\":5,\"id\":965478459,\"parentId\":1552039143}],\"parentN\":4,\"id\":1026718747,\"parentId\":798016924,\"missingNum\":true},{\"n\":-1,\"subCells\":[{\"n\":5,\"id\":-540862577,\"parentId\":-1745180883},{\"n\":8,\"id\":1725197877,\"parentId\":-1318518726}],\"parentN\":4,\"id\":1059057010,\"parentId\":798016924,\"missingNum\":true},{\"n\":6,\"parentN\":4,\"id\":935965605,\"parentId\":798016924,\"missingNum\":true},{\"n\":-1,\"subCells\":[{\"n\":1,\"id\":-196771001,\"parentId\":-158371264},{\"n\":2,\"id\":-268062293,\"parentId\":-1283840691},{\"n\":5,\"id\":1045487730,\"parentId\":2009095867}],\"parentN\":4,\"id\":285562572,\"parentId\":798016924,\"missingNum\":true},{\"n\":7,\"parentN\":4,\"id\":-1616787467,\"parentId\":798016924}],\"id\":2016149263,\"parentId\":798016924},{\"n\":5,\"subCells\":[{\"n\":1,\"parentN\":5,\"id\":-496679653,\"parentId\":436517925},{\"n\":-1,\"subCells\":[{\"n\":5,\"id\":1163111770,\"parentId\":699596913},{\"n\":8,\"id\":1840243904,\"parentId\":-1292862549}],\"parentN\":5,\"id\":-1916455756,\"parentId\":436517925,\"missingNum\":true},{\"n\":2,\"parentN\":5,\"id\":-235117007,\"parentId\":436517925,\"missingNum\":true},{\"n\":6,\"parentN\":5,\"id\":1939201039,\"parentId\":436517925,\"missingNum\":true},{\"n\":7,\"parentN\":5,\"id\":1800994831,\"parentId\":436517925,\"missingNum\":true},{\"n\":3,\"parentN\":5,\"id\":2006500386,\"parentId\":436517925},{\"n\":4,\"parentN\":5,\"id\":1168831951,\"parentId\":436517925},{\"n\":-1,\"subCells\":[{\"n\":5,\"id\":-1131195260,\"parentId\":-2092863138},{\"n\":8,\"id\":1375283386,\"parentId\":1540575108}],\"parentN\":5,\"id\":-1513804230,\"parentId\":436517925,\"missingNum\":true},{\"n\":9,\"parentN\":5,\"id\":264193007,\"parentId\":436517925,\"missingNum\":true}],\"id\":1223037439,\"parentId\":436517925},{\"n\":6,\"subCells\":[{\"n\":-1,\"subCells\":[{\"n\":6,\"id\":651889375,\"parentId\":1160636135},{\"n\":8,\"id\":504161099,\"parentId\":1786551093}],\"parentN\":6,\"id\":553809110,\"parentId\":-2094565750,\"missingNum\":true},{\"n\":-1,\"subCells\":[{\"n\":5,\"id\":1100107364,\"parentId\":-1563918885},{\"n\":6,\"id\":1213049029,\"parentId\":-1394598085}],\"parentN\":6,\"id\":1004785227,\"parentId\":-2094565750,\"missingNum\":true},{\"n\":7,\"parentN\":6,\"id\":718208236,\"parentId\":-2094565750},{\"n\":-1,\"subCells\":[{\"n\":1,\"id\":1138853055,\"parentId\":-1947623506},{\"n\":9,\"id\":608181925,\"parentId\":84415860}],\"parentN\":6,\"id\":1524177736,\"parentId\":-2094565750,\"missingNum\":true},{\"n\":-1,\"subCells\":[{\"n\":2,\"id\":488003913,\"parentId\":-371866001},{\"n\":5,\"id\":-1729694565,\"parentId\":-400608439},{\"n\":9,\"id\":-143413811,\"parentId\":-1709872836}],\"parentN\":6,\"id\":2126567093,\"parentId\":-2094565750,\"missingNum\":true},{\"n\":4,\"parentN\":6,\"id\":520402535,\"parentId\":-2094565750},{\"n\":-1,\"subCells\":[{\"n\":1,\"id\":1897829326,\"parentId\":708366535},{\"n\":8,\"id\":1153965400,\"parentId\":-1397891334}],\"parentN\":6,\"id\":1269363301,\"parentId\":-2094565750,\"missingNum\":true},{\"n\":3,\"parentN\":6,\"id\":1256376298,\"parentId\":-2094565750,\"missingNum\":true},{\"n\":-1,\"subCells\":[{\"n\":1,\"id\":-72124492,\"parentId\":94001660},{\"n\":2,\"id\":-724264223,\"parentId\":-737683145}],\"parentN\":6,\"id\":1089084860,\"parentId\":-2094565750,\"missingNum\":true}],\"id\":1379748822,\"parentId\":-2094565750},{\"n\":7,\"subCells\":[{\"n\":7,\"parentN\":7,\"id\":2072191110,\"parentId\":-1188886827,\"missingNum\":true},{\"n\":8,\"parentN\":7,\"id\":1837484848,\"parentId\":-1188886827},{\"n\":2,\"parentN\":7,\"id\":1515634666,\"parentId\":-1188886827,\"missingNum\":true},{\"n\":5,\"parentN\":7,\"id\":945958094,\"parentId\":-1188886827},{\"n\":4,\"parentN\":7,\"id\":-1121226470,\"parentId\":-1188886827,\"missingNum\":true},{\"n\":6,\"parentN\":7,\"id\":-469403318,\"parentId\":-1188886827,\"missingNum\":true},{\"n\":1,\"parentN\":7,\"id\":-466369402,\"parentId\":-1188886827},{\"n\":3,\"parentN\":7,\"id\":-1929502309,\"parentId\":-1188886827,\"missingNum\":true},{\"n\":9,\"parentN\":7,\"id\":1894224006,\"parentId\":-1188886827,\"missingNum\":true}],\"id\":1892274448,\"parentId\":-1188886827},{\"n\":8,\"subCells\":[{\"n\":3,\"parentN\":8,\"id\":646875274,\"parentId\":-872216602,\"missingNum\":true},{\"n\":9,\"parentN\":8,\"id\":-1121194118,\"parentId\":-872216602},{\"n\":5,\"parentN\":8,\"id\":-440330435,\"parentId\":-872216602},{\"n\":8,\"parentN\":8,\"id\":-1191217530,\"parentId\":-872216602,\"missingNum\":true},{\"n\":1,\"parentN\":8,\"id\":1793860480,\"parentId\":-872216602,\"missingNum\":true},{\"n\":7,\"parentN\":8,\"id\":911123137,\"parentId\":-872216602,\"missingNum\":true},{\"n\":2,\"parentN\":8,\"id\":-1461458499,\"parentId\":-872216602,\"missingNum\":true},{\"n\":6,\"parentN\":8,\"id\":-480283539,\"parentId\":-872216602},{\"n\":4,\"parentN\":8,\"id\":1610773607,\"parentId\":-872216602,\"missingNum\":true}],\"id\":-2049327903,\"parentId\":-872216602},{\"n\":9,\"subCells\":[{\"n\":-1,\"subCells\":[{\"n\":1,\"id\":88607285,\"parentId\":-1258180105},{\"n\":4,\"id\":2037149743,\"parentId\":-304839854},{\"n\":6,\"id\":1428835654,\"parentId\":-724097642}],\"parentN\":9,\"id\":-1289376325,\"parentId\":1550539273,\"missingNum\":true},{\"n\":-1,\"subCells\":[{\"n\":4,\"id\":-296650113,\"parentId\":869284955},{\"n\":6,\"id\":-1853571946,\"parentId\":1345201880}],\"parentN\":9,\"id\":-770223615,\"parentId\":1550539273,\"missingNum\":true},{\"n\":-1,\"subCells\":[{\"n\":1,\"id\":643116371,\"parentId\":482384742},{\"n\":6,\"id\":-1693904019,\"parentId\":1152763788}],\"parentN\":9,\"id\":-1115606668,\"parentId\":1550539273,\"missingNum\":true},{\"n\":2,\"parentN\":9,\"id\":253619641,\"parentId\":1550539273},{\"n\":-1,\"subCells\":[{\"n\":9,\"id\":-1308686787,\"parentId\":-1349248220}],\"parentN\":9,\"id\":-1141983528,\"parentId\":1550539273,\"missingNum\":true},{\"n\":3,\"parentN\":9,\"id\":-776707973,\"parentId\":1550539273},{\"n\":5,\"parentN\":9,\"id\":194560534,\"parentId\":1550539273,\"missingNum\":true},{\"n\":7,\"parentN\":9,\"id\":-1360639241,\"parentId\":1550539273,\"missingNum\":true},{\"n\":8,\"parentN\":9,\"id\":-1569440630,\"parentId\":1550539273,\"missingNum\":true}],\"id\":-1804328302,\"parentId\":1550539273}]","solvedBoardState":"[{\"n\":1,\"subCells\":[{\"n\":3,\"id\":11472637,\"parentId\":203341368},{\"n\":6,\"id\":-1182416716,\"parentId\":203341368},{\"n\":4,\"id\":-1799008309,\"parentId\":203341368},{\"n\":2,\"id\":1183477070,\"parentId\":203341368},{\"n\":5,\"id\":-725217624,\"parentId\":203341368},{\"n\":8,\"id\":741972555,\"parentId\":203341368},{\"n\":9,\"id\":-2110950828,\"parentId\":203341368},{\"n\":7,\"id\":-1160377174,\"parentId\":203341368},{\"n\":1,\"id\":1406069000,\"parentId\":203341368}],\"id\":1943305456,\"parentId\":203341368},{\"n\":2,\"subCells\":[{\"n\":9,\"parentN\":2,\"id\":-1167167144,\"parentId\":-33686898},{\"n\":2,\"parentN\":2,\"id\":-1962967205,\"parentId\":-33686898},{\"n\":8,\"parentN\":2,\"id\":161372328,\"parentId\":-33686898},{\"n\":7,\"parentN\":2,\"id\":1779247307,\"parentId\":-33686898},{\"n\":3,\"parentN\":2,\"id\":913432717,\"parentId\":-33686898},{\"n\":1,\"parentN\":2,\"id\":-383189130,\"parentId\":-33686898},{\"n\":5,\"parentN\":2,\"id\":1513557085,\"parentId\":-33686898},{\"n\":4,\"parentN\":2,\"id\":-613803086,\"parentId\":-33686898},{\"n\":6,\"parentN\":2,\"id\":-1013512856,\"parentId\":-33686898}],\"id\":821008397,\"parentId\":-33686898},{\"n\":3,\"subCells\":[{\"n\":7,\"parentN\":3,\"id\":-1672882008,\"parentId\":1901098076},{\"n\":1,\"parentN\":3,\"id\":891905781,\"parentId\":1901098076},{\"n\":5,\"parentN\":3,\"id\":1615748341,\"parentId\":1901098076},{\"n\":4,\"parentN\":3,\"id\":705426214,\"parentId\":1901098076},{\"n\":6,\"parentN\":3,\"id\":-683940266,\"parentId\":1901098076},{\"n\":9,\"parentN\":3,\"id\":-423110521,\"parentId\":1901098076},{\"n\":3,\"parentN\":3,\"id\":294837882,\"parentId\":1901098076},{\"n\":8,\"parentN\":3,\"id\":-1762633619,\"parentId\":1901098076},{\"n\":2,\"parentN\":3,\"id\":1337742053,\"parentId\":1901098076}],\"id\":837352339,\"parentId\":1901098076},{\"n\":4,\"subCells\":[{\"n\":4,\"parentN\":4,\"id\":-1918679084,\"parentId\":1012833831},{\"n\":9,\"parentN\":4,\"id\":1348624336,\"parentId\":1012833831},{\"n\":3,\"parentN\":4,\"id\":-1080368755,\"parentId\":1012833831},{\"n\":8,\"parentN\":4,\"id\":-736871314,\"parentId\":1012833831},{\"n\":1,\"parentN\":4,\"id\":593945973,\"parentId\":1012833831},{\"n\":5,\"parentN\":4,\"id\":1780501538,\"parentId\":1012833831},{\"n\":6,\"parentN\":4,\"id\":-1112581535,\"parentId\":1012833831},{\"n\":2,\"parentN\":4,\"id\":-1875598026,\"parentId\":1012833831},{\"n\":7,\"parentN\":4,\"id\":641951289,\"parentId\":1012833831}],\"id\":1267443983,\"parentId\":1012833831},{\"n\":5,\"subCells\":[{\"n\":1,\"parentN\":5,\"id\":-890480443,\"parentId\":1725423451},{\"n\":8,\"parentN\":5,\"id\":-1225438207,\"parentId\":1725423451},{\"n\":2,\"parentN\":5,\"id\":456555770,\"parentId\":1725423451},{\"n\":6,\"parentN\":5,\"id\":-1593080040,\"parentId\":1725423451},{\"n\":7,\"parentN\":5,\"id\":-1556363758,\"parentId\":1725423451},{\"n\":3,\"parentN\":5,\"id\":1131707430,\"parentId\":1725423451},{\"n\":4,\"parentN\":5,\"id\":1431635546,\"parentId\":1725423451},{\"n\":5,\"parentN\":5,\"id\":578847686,\"parentId\":1725423451},{\"n\":9,\"parentN\":5,\"id\":993323628,\"parentId\":1725423451}],\"id\":-427231355,\"parentId\":1725423451},{\"n\":6,\"subCells\":[{\"n\":6,\"parentN\":6,\"id\":-809423787,\"parentId\":493962433},{\"n\":5,\"parentN\":6,\"id\":688243966,\"parentId\":493962433},{\"n\":7,\"parentN\":6,\"id\":-763759652,\"parentId\":493962433},{\"n\":9,\"parentN\":6,\"id\":1643577853,\"parentId\":493962433},{\"n\":2,\"parentN\":6,\"id\":1620539318,\"parentId\":493962433},{\"n\":4,\"parentN\":6,\"id\":-125087627,\"parentId\":493962433},{\"n\":8,\"parentN\":6,\"id\":-746989837,\"parentId\":493962433},{\"n\":3,\"parentN\":6,\"id\":935071626,\"parentId\":493962433},{\"n\":1,\"parentN\":6,\"id\":12872817,\"parentId\":493962433}],\"id\":1522233698,\"parentId\":493962433},{\"n\":7,\"subCells\":[{\"n\":7,\"parentN\":7,\"id\":-550457871,\"parentId\":-2144978982},{\"n\":8,\"parentN\":7,\"id\":-500001516,\"parentId\":-2144978982},{\"n\":2,\"parentN\":7,\"id\":-506651682,\"parentId\":-2144978982},{\"n\":5,\"parentN\":7,\"id\":1550060660,\"parentId\":-2144978982},{\"n\":4,\"parentN\":7,\"id\":999434115,\"parentId\":-2144978982},{\"n\":6,\"parentN\":7,\"id\":1947018208,\"parentId\":-2144978982},{\"n\":1,\"parentN\":7,\"id\":-165881329,\"parentId\":-2144978982},{\"n\":3,\"parentN\":7,\"id\":-1299452162,\"parentId\":-2144978982},{\"n\":9,\"parentN\":7,\"id\":1180045768,\"parentId\":-2144978982}],\"id\":-1744378259,\"parentId\":-2144978982},{\"n\":8,\"subCells\":[{\"n\":3,\"parentN\":8,\"id\":658055264,\"parentId\":2044874139},{\"n\":9,\"parentN\":8,\"id\":1337937006,\"parentId\":2044874139},{\"n\":5,\"parentN\":8,\"id\":-872164110,\"parentId\":2044874139},{\"n\":8,\"parentN\":8,\"id\":-2025728767,\"parentId\":2044874139},{\"n\":1,\"parentN\":8,\"id\":360242913,\"parentId\":2044874139},{\"n\":7,\"parentN\":8,\"id\":1461249256,\"parentId\":2044874139},{\"n\":2,\"parentN\":8,\"id\":-680333662,\"parentId\":2044874139},{\"n\":6,\"parentN\":8,\"id\":-1448789947,\"parentId\":2044874139},{\"n\":4,\"parentN\":8,\"id\":-1979080830,\"parentId\":2044874139}],\"id\":1330555729,\"parentId\":2044874139},{\"n\":9,\"subCells\":[{\"n\":1,\"parentN\":9,\"id\":-1635622402,\"parentId\":57090152},{\"n\":4,\"parentN\":9,\"id\":735555213,\"parentId\":57090152},{\"n\":6,\"parentN\":9,\"id\":-267554700,\"parentId\":57090152},{\"n\":2,\"parentN\":9,\"id\":2102426347,\"parentId\":57090152},{\"n\":9,\"parentN\":9,\"id\":937992534,\"parentId\":57090152},{\"n\":3,\"parentN\":9,\"id\":-1923342388,\"parentId\":57090152},{\"n\":5,\"parentN\":9,\"id\":-753567215,\"parentId\":57090152},{\"n\":7,\"parentN\":9,\"id\":1484362383,\"parentId\":57090152},{\"n\":8,\"parentN\":9,\"id\":-1536833654,\"parentId\":57090152}],\"id\":-859909726,\"parentId\":57090152}]","seconds":76,"difficulty":0,"scores":[{"id":656472079,"date":1777861127639,"time":340,"difficulty":5,"missingDigits":58,"completedBoard":"364928715258731469971546382493182657815673924627459831782395146546817293139264578"},{"id":151217165,"date":1776936853042,"time":165,"difficulty":4,"missingDigits":56,"completedBoard":"972861543135794682468235971241953768693187425857426139586349217314572896729618354"}]}