{"lastModified":1779661222976,"boardState":"[{\"n\":1,\"subCells\":[{\"n\":9,\"id\":-1443231648,\"parentId\":-1114428717},{\"n\":7,\"id\":-1934644575,\"parentId\":-1114428717,\"missingNum\":true},{\"n\":3,\"id\":-373778470,\"parentId\":-1114428717,\"missingNum\":true},{\"n\":6,\"id\":194483713,\"parentId\":-1114428717},{\"n\":2,\"id\":1223768523,\"parentId\":-1114428717},{\"n\":-1,\"subCells\":[{\"n\":1,\"id\":-1105457812,\"parentId\":2128885637}],\"id\":-305789575,\"parentId\":-1114428717,\"missingNum\":true},{\"n\":8,\"id\":-96163581,\"parentId\":-1114428717,\"missingNum\":true},{\"n\":4,\"id\":1878008324,\"parentId\":-1114428717,\"missingNum\":true},{\"n\":5,\"id\":2030799537,\"parentId\":-1114428717}],\"id\":1720637478,\"parentId\":-1114428717},{\"n\":2,\"subCells\":[{\"n\":5,\"parentN\":2,\"id\":1588735713,\"parentId\":-2049911621},{\"n\":-1,\"subCells\":[{\"n\":4,\"id\":-803688246,\"parentId\":729652294},{\"n\":6,\"id\":-1744235482,\"parentId\":-1316016667}],\"parentN\":2,\"id\":718340476,\"parentId\":-2049911621,\"missingNum\":true},{\"n\":-1,\"subCells\":[{\"n\":6,\"id\":348137474,\"parentId\":-1722213801},{\"n\":8,\"id\":762092924,\"parentId\":2029248623}],\"parentN\":2,\"id\":-1195802866,\"parentId\":-2049911621,\"missingNum\":true},{\"n\":7,\"parentN\":2,\"id\":-544409918,\"parentId\":-2049911621},{\"n\":-1,\"subCells\":[{\"n\":1,\"id\":-1193239398,\"parentId\":827224625},{\"n\":4,\"id\":-730377683,\"parentId\":-757752742}],\"parentN\":2,\"id\":-2020878418,\"parentId\":-2049911621,\"missingNum\":true},{\"n\":-1,\"subCells\":[{\"n\":3,\"id\":1000607263,\"parentId\":692191196},{\"n\":8,\"id\":181240709,\"parentId\":1523589421}],\"parentN\":2,\"id\":1022991020,\"parentId\":-2049911621,\"missingNum\":true},{\"n\":-1,\"subCells\":[{\"n\":2,\"id\":186959188,\"parentId\":1580514378},{\"n\":3,\"id\":257622933,\"parentId\":-1465245589},{\"n\":9,\"id\":-1245460960,\"parentId\":1778654639}],\"parentN\":2,\"id\":274594737,\"parentId\":-2049911621,\"missingNum\":true},{\"n\":-1,\"subCells\":[{\"n\":1,\"id\":-312643489,\"parentId\":-754704190},{\"n\":2,\"id\":-1071997180,\"parentId\":-117437118},{\"n\":9,\"id\":-1852565090,\"parentId\":-127311572}],\"parentN\":2,\"id\":399051370,\"parentId\":-2049911621,\"missingNum\":true},{\"n\":-1,\"subCells\":[{\"n\":2,\"id\":-1646467197,\"parentId\":219400277},{\"n\":3,\"id\":-391290669,\"parentId\":288490247},{\"n\":9,\"id\":-1649084862,\"parentId\":-691415776}],\"parentN\":2,\"id\":1113554361,\"parentId\":-2049911621,\"missingNum\":true}],\"id\":-448919572,\"parentId\":-2049911621},{\"n\":3,\"subCells\":[{\"n\":2,\"parentN\":3,\"id\":-807114522,\"parentId\":-1102495273,\"missingNum\":true},{\"n\":-1,\"subCells\":[{\"n\":4,\"id\":670523134,\"parentId\":80313623},{\"n\":8,\"id\":829005802,\"parentId\":-377655010}],\"parentN\":3,\"id\":-1261825976,\"parentId\":-1102495273,\"missingNum\":true},{\"n\":1,\"parentN\":3,\"id\":-51926138,\"parentId\":-1102495273,\"missingNum\":true},{\"n\":5,\"parentN\":3,\"id\":1901126591,\"parentId\":-1102495273},{\"n\":-1,\"subCells\":[{\"n\":3,\"id\":-1743904272,\"parentId\":-1385519072},{\"n\":4,\"id\":-1851536158,\"parentId\":48633911},{\"n\":8,\"id\":1411816550,\"parentId\":1073921666}],\"parentN\":3,\"id\":-250547875,\"parentId\":-1102495273,\"missingNum\":true},{\"n\":9,\"parentN\":3,\"id\":-2006222047,\"parentId\":-1102495273,\"missingNum\":true},{\"n\":6,\"parentN\":3,\"id\":-935312842,\"parentId\":-1102495273},{\"n\":-1,\"subCells\":[{\"n\":3,\"id\":-2049857552,\"parentId\":1814804105}],\"parentN\":3,\"id\":-5776760,\"parentId\":-1102495273,\"missingNum\":true},{\"n\":7,\"parentN\":3,\"id\":-119063203,\"parentId\":-1102495273}],\"id\":552488231,\"parentId\":-1102495273},{\"n\":4,\"subCells\":[{\"n\":1,\"parentN\":4,\"id\":514031800,\"parentId\":648103551,\"missingNum\":true},{\"n\":9,\"parentN\":4,\"id\":-1324077935,\"parentId\":648103551,\"missingNum\":true},{\"n\":6,\"parentN\":4,\"id\":-151283260,\"parentId\":648103551},{\"n\":2,\"parentN\":4,\"id\":2073904030,\"parentId\":648103551},{\"n\":5,\"parentN\":4,\"id\":293833214,\"parentId\":648103551,\"missingNum\":true},{\"n\":7,\"parentN\":4,\"id\":217646337,\"parentId\":648103551,\"missingNum\":true},{\"n\":3,\"parentN\":4,\"id\":2085861764,\"parentId\":648103551,\"missingNum\":true},{\"n\":8,\"parentN\":4,\"id\":1427283250,\"parentId\":648103551},{\"n\":4,\"parentN\":4,\"id\":1830890401,\"parentId\":648103551,\"missingNum\":true}],\"id\":1167218524,\"parentId\":648103551},{\"n\":5,\"subCells\":[{\"n\":8,\"parentN\":5,\"id\":1860938968,\"parentId\":1417362117,\"missingNum\":true},{\"n\":7,\"parentN\":5,\"id\":1656100442,\"parentId\":1417362117,\"missingNum\":true},{\"n\":4,\"parentN\":5,\"id\":1105356839,\"parentId\":1417362117},{\"n\":-1,\"subCells\":[{\"n\":6,\"id\":-1789596126,\"parentId\":-707816127}],\"parentN\":5,\"id\":-1985962015,\"parentId\":1417362117,\"missingNum\":true},{\"n\":3,\"parentN\":5,\"id\":1842130727,\"parentId\":1417362117},{\"n\":1,\"parentN\":5,\"id\":-250099586,\"parentId\":1417362117,\"missingNum\":true},{\"n\":-1,\"subCells\":[{\"n\":2,\"id\":-2040868352,\"parentId\":589487855},{\"n\":6,\"id\":-447597487,\"parentId\":-1929692243},{\"n\":9,\"id\":-1754057421,\"parentId\":-1477376760}],\"parentN\":5,\"id\":-2014629654,\"parentId\":1417362117,\"missingNum\":true},{\"n\":-1,\"subCells\":[{\"n\":2,\"id\":-917335914,\"parentId\":-427535819},{\"n\":5,\"id\":-472770178,\"parentId\":-1539656082},{\"n\":6,\"id\":-312798384,\"parentId\":2114869132},{\"n\":9,\"id\":-1062035446,\"parentId\":285470328}],\"parentN\":5,\"id\":-1964896443,\"parentId\":1417362117,\"missingNum\":true},{\"n\":-1,\"subCells\":[{\"n\":2,\"id\":-1514820488,\"parentId\":330697450},{\"n\":5,\"id\":-543526058,\"parentId\":-846772823},{\"n\":6,\"id\":-1952747893,\"parentId\":1927119677},{\"n\":9,\"id\":-830400142,\"parentId\":-340875988}],\"parentN\":5,\"id\":-60820465,\"parentId\":1417362117,\"missingNum\":true}],\"id\":-986526621,\"parentId\":1417362117},{\"n\":6,\"subCells\":[{\"n\":3,\"parentN\":6,\"id\":-96614223,\"parentId\":-205313109,\"missingNum\":true},{\"n\":5,\"parentN\":6,\"id\":-136173712,\"parentId\":-205313109,\"missingNum\":true},{\"n\":2,\"parentN\":6,\"id\":-88973646,\"parentId\":-205313109,\"missingNum\":true},{\"n\":8,\"parentN\":6,\"id\":-1390596903,\"parentId\":-205313109,\"missingNum\":true},{\"n\":9,\"parentN\":6,\"id\":1664294082,\"parentId\":-205313109},{\"n\":4,\"parentN\":6,\"id\":545131073,\"parentId\":-205313109,\"missingNum\":true},{\"n\":7,\"parentN\":6,\"id\":264060545,\"parentId\":-205313109,\"missingNum\":true},{\"n\":1,\"parentN\":6,\"id\":-1366936024,\"parentId\":-205313109},{\"n\":-1,\"subCells\":[{\"n\":6,\"id\":-1241264888,\"parentId\":-191070100}],\"parentN\":6,\"id\":1466769114,\"parentId\":-205313109,\"missingNum\":true}],\"id\":969029259,\"parentId\":-205313109},{\"n\":7,\"subCells\":[{\"n\":4,\"parentN\":7,\"id\":-135708483,\"parentId\":-242488851},{\"n\":-1,\"subCells\":[{\"n\":1,\"id\":1878080246,\"parentId\":-1296390818},{\"n\":3,\"id\":-2122206822,\"parentId\":310286645}],\"parentN\":7,\"id\":1759851139,\"parentId\":-242488851,\"missingNum\":true},{\"n\":-1,\"subCells\":[{\"n\":1,\"id\":-95073045,\"parentId\":1560623654},{\"n\":2,\"id\":1842195129,\"parentId\":-212484323},{\"n\":9,\"id\":1383213612,\"parentId\":1361396622}],\"parentN\":7,\"id\":-1756095462,\"parentId\":-242488851,\"missingNum\":true},{\"n\":5,\"parentN\":7,\"id\":-1542923233,\"parentId\":-242488851,\"missingNum\":true},{\"n\":6,\"parentN\":7,\"id\":1196441205,\"parentId\":-242488851,\"missingNum\":true},{\"n\":-1,\"subCells\":[{\"n\":2,\"id\":2081830150,\"parentId\":-613061612},{\"n\":9,\"id\":2142431136,\"parentId\":1396701077}],\"parentN\":7,\"id\":-649596584,\"parentId\":-242488851,\"missingNum\":true},{\"n\":7,\"parentN\":7,\"id\":-1872736783,\"parentId\":-242488851},{\"n\":-1,\"subCells\":[{\"n\":1,\"id\":373002579,\"parentId\":-1148196092},{\"n\":3,\"id\":1213181078,\"parentId\":-744366102}],\"parentN\":7,\"id\":-1531864097,\"parentId\":-242488851,\"missingNum\":true},{\"n\":8,\"parentN\":7,\"id\":1009534746,\"parentId\":-242488851,\"missingNum\":true}],\"id\":-355372532,\"parentId\":-242488851},{\"n\":8,\"subCells\":[{\"n\":-1,\"subCells\":[{\"n\":2,\"id\":-464266628,\"parentId\":-744076816},{\"n\":3,\"id\":-451723282,\"parentId\":467915233},{\"n\":9,\"id\":1205640869,\"parentId\":1916054041}],\"parentN\":8,\"id\":921743130,\"parentId\":-609054503,\"missingNum\":true},{\"n\":-1,\"subCells\":[{\"n\":2,\"id\":792373102,\"parentId\":-1322883357},{\"n\":5,\"id\":-290633935,\"parentId\":1518003310},{\"n\":9,\"id\":-150789281,\"parentId\":-1290981862}],\"parentN\":8,\"id\":-1009596841,\"parentId\":-609054503,\"missingNum\":true},{\"n\":7,\"parentN\":8,\"id\":2036036584,\"parentId\":-609054503,\"missingNum\":true},{\"n\":1,\"parentN\":8,\"id\":1461457580,\"parentId\":-609054503},{\"n\":8,\"parentN\":8,\"id\":1014295502,\"parentId\":-609054503},{\"n\":-1,\"subCells\":[{\"n\":2,\"id\":-1683196066,\"parentId\":-238209853},{\"n\":9,\"id\":244374696,\"parentId\":125388233}],\"parentN\":8,\"id\":580599481,\"parentId\":-609054503,\"missingNum\":true},{\"n\":4,\"parentN\":8,\"id\":-451368865,\"parentId\":-609054503,\"missingNum\":true},{\"n\":-1,\"subCells\":[{\"n\":6,\"id\":-556359108,\"parentId\":-1732803034},{\"n\":9,\"id\":1796677848,\"parentId\":-1886191103}],\"parentN\":8,\"id\":-559876103,\"parentId\":-609054503,\"missingNum\":true},{\"n\":-1,\"subCells\":[{\"n\":3,\"id\":2015207113,\"parentId\":-1537975026},{\"n\":6,\"id\":-1255563006,\"parentId\":-2120735577},{\"n\":9,\"id\":1587674643,\"parentId\":-1260881568}],\"parentN\":8,\"id\":834244121,\"parentId\":-609054503,\"missingNum\":true}],\"id\":1993818725,\"parentId\":-609054503},{\"n\":9,\"subCells\":[{\"n\":-1,\"subCells\":[{\"n\":1,\"id\":-108479403,\"parentId\":-2050129099},{\"n\":9,\"id\":328432888,\"parentId\":-2037729707}],\"parentN\":9,\"id\":20804551,\"parentId\":506922154,\"missingNum\":true},{\"n\":6,\"parentN\":9,\"id\":-1798030891,\"parentId\":506922154,\"missingNum\":true},{\"n\":8,\"parentN\":9,\"id\":-1724311623,\"parentId\":506922154},{\"n\":4,\"parentN\":9,\"id\":1959190117,\"parentId\":506922154},{\"n\":7,\"parentN\":9,\"id\":-45118680,\"parentId\":506922154,\"missingNum\":true},{\"n\":3,\"parentN\":9,\"id\":-815746823,\"parentId\":506922154,\"missingNum\":true},{\"n\":-1,\"subCells\":[{\"n\":1,\"id\":-2026579859,\"parentId\":-1915660947},{\"n\":9,\"id\":1980156316,\"parentId\":882902438}],\"parentN\":9,\"id\":-251451972,\"parentId\":506922154,\"missingNum\":true},{\"n\":2,\"parentN\":9,\"id\":295384326,\"parentId\":506922154},{\"n\":5,\"parentN\":9,\"id\":-1220802475,\"parentId\":506922154,\"missingNum\":true}],\"id\":1480742042,\"parentId\":506922154}]","solvedBoardState":"[{\"n\":1,\"subCells\":[{\"n\":9,\"id\":-2049801145,\"parentId\":755443311},{\"n\":7,\"id\":1710035855,\"parentId\":755443311},{\"n\":3,\"id\":-832900986,\"parentId\":755443311},{\"n\":6,\"id\":-729987185,\"parentId\":755443311},{\"n\":2,\"id\":-659855103,\"parentId\":755443311},{\"n\":1,\"id\":949895668,\"parentId\":755443311},{\"n\":8,\"id\":-1576081358,\"parentId\":755443311},{\"n\":4,\"id\":1833084354,\"parentId\":755443311},{\"n\":5,\"id\":1306319227,\"parentId\":755443311}],\"id\":491268695,\"parentId\":755443311},{\"n\":2,\"subCells\":[{\"n\":5,\"parentN\":2,\"id\":-19873544,\"parentId\":-798125509},{\"n\":6,\"parentN\":2,\"id\":12409093,\"parentId\":-798125509},{\"n\":8,\"parentN\":2,\"id\":465029345,\"parentId\":-798125509},{\"n\":7,\"parentN\":2,\"id\":-1771856840,\"parentId\":-798125509},{\"n\":4,\"parentN\":2,\"id\":-1647422270,\"parentId\":-798125509},{\"n\":3,\"parentN\":2,\"id\":1371113172,\"parentId\":-798125509},{\"n\":2,\"parentN\":2,\"id\":1665717788,\"parentId\":-798125509},{\"n\":1,\"parentN\":2,\"id\":-1825659760,\"parentId\":-798125509},{\"n\":9,\"parentN\":2,\"id\":-1036265415,\"parentId\":-798125509}],\"id\":-1228697269,\"parentId\":-798125509},{\"n\":3,\"subCells\":[{\"n\":2,\"parentN\":3,\"id\":2063305207,\"parentId\":-1147910701},{\"n\":4,\"parentN\":3,\"id\":1193999081,\"parentId\":-1147910701},{\"n\":1,\"parentN\":3,\"id\":1800071599,\"parentId\":-1147910701},{\"n\":5,\"parentN\":3,\"id\":909249501,\"parentId\":-1147910701},{\"n\":8,\"parentN\":3,\"id\":-942888382,\"parentId\":-1147910701},{\"n\":9,\"parentN\":3,\"id\":-1464084439,\"parentId\":-1147910701},{\"n\":6,\"parentN\":3,\"id\":-1011829489,\"parentId\":-1147910701},{\"n\":3,\"parentN\":3,\"id\":-1753367191,\"parentId\":-1147910701},{\"n\":7,\"parentN\":3,\"id\":2039850798,\"parentId\":-1147910701}],\"id\":-1442227046,\"parentId\":-1147910701},{\"n\":4,\"subCells\":[{\"n\":1,\"parentN\":4,\"id\":562097009,\"parentId\":-2020057568},{\"n\":9,\"parentN\":4,\"id\":-701077247,\"parentId\":-2020057568},{\"n\":6,\"parentN\":4,\"id\":-1908158119,\"parentId\":-2020057568},{\"n\":2,\"parentN\":4,\"id\":222366016,\"parentId\":-2020057568},{\"n\":5,\"parentN\":4,\"id\":347108971,\"parentId\":-2020057568},{\"n\":7,\"parentN\":4,\"id\":1346471497,\"parentId\":-2020057568},{\"n\":3,\"parentN\":4,\"id\":-1079386604,\"parentId\":-2020057568},{\"n\":8,\"parentN\":4,\"id\":1659724220,\"parentId\":-2020057568},{\"n\":4,\"parentN\":4,\"id\":-1849263795,\"parentId\":-2020057568}],\"id\":1990444114,\"parentId\":-2020057568},{\"n\":5,\"subCells\":[{\"n\":8,\"parentN\":5,\"id\":-443205207,\"parentId\":-1768364158},{\"n\":7,\"parentN\":5,\"id\":-1700434566,\"parentId\":-1768364158},{\"n\":4,\"parentN\":5,\"id\":-367569299,\"parentId\":-1768364158},{\"n\":6,\"parentN\":5,\"id\":597269391,\"parentId\":-1768364158},{\"n\":3,\"parentN\":5,\"id\":745820833,\"parentId\":-1768364158},{\"n\":1,\"parentN\":5,\"id\":-2042576439,\"parentId\":-1768364158},{\"n\":9,\"parentN\":5,\"id\":-546050947,\"parentId\":-1768364158},{\"n\":2,\"parentN\":5,\"id\":2044969301,\"parentId\":-1768364158},{\"n\":5,\"parentN\":5,\"id\":1858030365,\"parentId\":-1768364158}],\"id\":1937385598,\"parentId\":-1768364158},{\"n\":6,\"subCells\":[{\"n\":3,\"parentN\":6,\"id\":736910975,\"parentId\":-1063697703},{\"n\":5,\"parentN\":6,\"id\":291270950,\"parentId\":-1063697703},{\"n\":2,\"parentN\":6,\"id\":1914359392,\"parentId\":-1063697703},{\"n\":8,\"parentN\":6,\"id\":776178540,\"parentId\":-1063697703},{\"n\":9,\"parentN\":6,\"id\":-444769419,\"parentId\":-1063697703},{\"n\":4,\"parentN\":6,\"id\":-168661590,\"parentId\":-1063697703},{\"n\":7,\"parentN\":6,\"id\":-334435290,\"parentId\":-1063697703},{\"n\":1,\"parentN\":6,\"id\":-868342376,\"parentId\":-1063697703},{\"n\":6,\"parentN\":6,\"id\":-99736175,\"parentId\":-1063697703}],\"id\":-2056354230,\"parentId\":-1063697703},{\"n\":7,\"subCells\":[{\"n\":4,\"parentN\":7,\"id\":2027245136,\"parentId\":270731300},{\"n\":1,\"parentN\":7,\"id\":-472778017,\"parentId\":270731300},{\"n\":2,\"parentN\":7,\"id\":-643444590,\"parentId\":270731300},{\"n\":5,\"parentN\":7,\"id\":2141460020,\"parentId\":270731300},{\"n\":6,\"parentN\":7,\"id\":1582454350,\"parentId\":270731300},{\"n\":9,\"parentN\":7,\"id\":-63847928,\"parentId\":270731300},{\"n\":7,\"parentN\":7,\"id\":-168527599,\"parentId\":270731300},{\"n\":3,\"parentN\":7,\"id\":1781501804,\"parentId\":270731300},{\"n\":8,\"parentN\":7,\"id\":665587000,\"parentId\":270731300}],\"id\":950257926,\"parentId\":270731300},{\"n\":8,\"subCells\":[{\"n\":3,\"parentN\":8,\"id\":2013011562,\"parentId\":-2145353391},{\"n\":5,\"parentN\":8,\"id\":1029199195,\"parentId\":-2145353391},{\"n\":7,\"parentN\":8,\"id\":701982680,\"parentId\":-2145353391},{\"n\":1,\"parentN\":8,\"id\":-466133170,\"parentId\":-2145353391},{\"n\":8,\"parentN\":8,\"id\":-335915545,\"parentId\":-2145353391},{\"n\":2,\"parentN\":8,\"id\":-678419438,\"parentId\":-2145353391},{\"n\":4,\"parentN\":8,\"id\":-782834742,\"parentId\":-2145353391},{\"n\":9,\"parentN\":8,\"id\":740806392,\"parentId\":-2145353391},{\"n\":6,\"parentN\":8,\"id\":1565274799,\"parentId\":-2145353391}],\"id\":102990457,\"parentId\":-2145353391},{\"n\":9,\"subCells\":[{\"n\":9,\"parentN\":9,\"id\":1187388147,\"parentId\":950324786},{\"n\":6,\"parentN\":9,\"id\":-891125472,\"parentId\":950324786},{\"n\":8,\"parentN\":9,\"id\":-1700385154,\"parentId\":950324786},{\"n\":4,\"parentN\":9,\"id\":-963076437,\"parentId\":950324786},{\"n\":7,\"parentN\":9,\"id\":1673661745,\"parentId\":950324786},{\"n\":3,\"parentN\":9,\"id\":2008293666,\"parentId\":950324786},{\"n\":1,\"parentN\":9,\"id\":-2026529727,\"parentId\":950324786},{\"n\":2,\"parentN\":9,\"id\":-199230456,\"parentId\":950324786},{\"n\":5,\"parentN\":9,\"id\":950302124,\"parentId\":950324786}],\"id\":-810218871,\"parentId\":950324786}]","seconds":1159,"difficulty":4,"scores":[{"id":-703886078,"date":1778222027052,"time":543,"difficulty":4,"missingDigits":56,"completedBoard":"735918624146732589829465317564381972291657438387294165978143256612579843453826791"},{"id":151217165,"date":1776936853042,"time":165,"difficulty":4,"missingDigits":56,"completedBoard":"972861543135794682468235971241953768693187425857426139586349217314572896729618354"},{"id":187323876,"date":1778469339889,"time":361,"difficulty":4,"missingDigits":58,"completedBoard":""},{"id":-159396814,"date":1778472261350,"time":92,"difficulty":2,"missingDigits":48,"completedBoard":""},{"id":1233583426,"date":1778607871282,"time":778,"difficulty":4,"missingDigits":56,"completedBoard":"915324687683597142724816395478269513256138974391745826137682459842953761569471238"},{"id":-409951165,"date":1778705458285,"time":1325,"difficulty":4,"missingDigits":58,"completedBoard":""},{"id":405857104,"date":1778776091858,"time":347,"difficulty":4,"missingDigits":57,"completedBoard":""},{"id":1877525933,"date":1778865179887,"time":335,"difficulty":4,"missingDigits":57,"completedBoard":""},{"id":1196425237,"date":1778938440142,"time":731,"difficulty":4,"missingDigits":57,"completedBoard":""},{"id":-356241603,"date":1779110507996,"time":1026,"difficulty":4,"missingDigits":56,"completedBoard":""},{"id":-1495627644,"date":1779201920025,"time":354,"difficulty":4,"missingDigits":56,"completedBoard":""},{"id":-1449081674,"date":1779306665931,"time":260,"difficulty":4,"missingDigits":56,"completedBoard":""},{"id":-1312438008,"date":1779407169075,"time":974,"difficulty":4,"missingDigits":56,"completedBoard":""},{"id":-268510140,"date":1779470566505,"time":343,"difficulty":4,"missingDigits":57,"completedBoard":""}],"deletedScoreIds":[-1797968752,552743655,656472079,1373817844,-873891452,-1591533259]}